bisecter/__init__.py
bisecter/__main__.py
bisecter/utils.py
bisecter-0.9.data/scripts/bisecter
bisecter-0.9.dist-info/LICENSE
bisecter-0.9.dist-info/METADATA
bisecter-0.9.dist-info/WHEEL
bisecter-0.9.dist-info/top_level.txt
bisecter-0.9.dist-info/RECORD
