Metadata-Version: 2.1
Name: bisecter
Version: 0.9
Summary: Allows to bisect over arbitrary number of arguments.
Home-page: https://github.com/ldoktor/bisecter
Author: Lukas Doktor
Author-email: ldoktor@redhat.com
License: GPLv2+
Platform: UNKNOWN
Classifier: Development Status :: 2 - Pre-Alpha
Classifier: Intended Audience :: Developers
Classifier: License :: OSI Approved :: GNU General Public License v2 or later (GPLv2+)
Classifier: Natural Language :: English
Classifier: Operating System :: POSIX
Classifier: Topic :: Software Development :: Testing
Classifier: Programming Language :: Python :: 3
Requires-Python: >=3.5
License-File: LICENSE
